rgi/__init__.py
rgi/geopackage/__init__.py
rgi/geopackage/geopackage.py
rgi/geopackage/nsg_geopackage.py
rgi/geopackage/common/__init__.py
rgi/geopackage/common/bounding_box.py
rgi/geopackage/common/tile_coordinate.py
rgi/geopackage/common/tile_scheme.py
rgi/geopackage/common/zoom_metadata.py
rgi/geopackage/common/zoom_times_two.py
rgi/geopackage/core/__init__.py
rgi/geopackage/core/content_entry.py
rgi/geopackage/core/geopackage_core_table_adapter.py
rgi/geopackage/core/spatial_ref_system_entry.py
rgi/geopackage/extensions/__init__.py
rgi/geopackage/extensions/extension_entry.py
rgi/geopackage/extensions/geopackage_extensions_table_adapter.py
rgi/geopackage/extensions/metadata/__init__.py
rgi/geopackage/extensions/metadata/geopackage_metadata_table_adapter.py
rgi/geopackage/extensions/metadata/md_scope.py
rgi/geopackage/extensions/metadata/metadata_entry.py
rgi/geopackage/extensions/metadata/metadata_reference/__init__.py
rgi/geopackage/extensions/metadata/metadata_reference/geopackage_metadata_reference_table_adapter.py
rgi/geopackage/extensions/metadata/metadata_reference/metadata_reference_entry.py
rgi/geopackage/extensions/metadata/metadata_reference/reference_scope.py
rgi/geopackage/extensions/vector_tiles/__init__.py
rgi/geopackage/extensions/vector_tiles/geopackage_geojson_vector_tiles_table_adapter.py
rgi/geopackage/extensions/vector_tiles/geopackage_mapbox_vector_tiles_table_adapter.py
rgi/geopackage/extensions/vector_tiles/geopackage_vector_tiles_table_adapter.py
rgi/geopackage/extensions/vector_tiles/vector_tiles_constants.py
rgi/geopackage/extensions/vector_tiles/vector_tiles_content_entry.py
rgi/geopackage/extensions/vector_tiles/vector_fields/__init__.py
rgi/geopackage/extensions/vector_tiles/vector_fields/geopackage_vector_fields_table_adapter.py
rgi/geopackage/extensions/vector_tiles/vector_fields/vector_fields_entry.py
rgi/geopackage/extensions/vector_tiles/vector_layers/__init__.py
geopackage_python-2.2.0.2.dist-info/METADATA
geopackage_python-2.2.0.2.dist-info/WHEEL
geopackage_python-2.2.0.2.dist-info/top_level.txt
geopackage_python-2.2.0.2.dist-info/RECORD
