Metadata-Version: 2.1
Name: geopackage-python
Version: 2.2.0.2
Summary: Python-based tools for creating OGC GeoPackages.
Home-page: https://gitlab.com/GitLabRGI/erdc/geopackage-python
Author: Reinventing Geospatial Inc (RGi), Steven Lander, Jenifer Cochran
Author-email: developer.publishers@rgi-corp.com
License: The MIT License (MIT)             
Platform: UNKNOWN
Classifier: Development Status :: 4 - Beta
Classifier: Intended Audience :: Developers
Classifier: Topic :: Software Development :: Build Tools
Classifier: License :: OSI Approved :: MIT License
Classifier: Programming Language :: Python :: 2.7
Classifier: Programming Language :: Python :: 3
Classifier: Programming Language :: Python :: 3.4
Classifier: Programming Language :: Python :: 3.5
Classifier: Programming Language :: Python :: 3.6
Classifier: Programming Language :: Python :: 3.7
Requires-Dist: defusedxml
Requires-Dist: lxml
Requires-Dist: Pillow
Requires-Dist: pytest (==4.6.3)
Requires-Dist: pytest-cov
Requires-Dist: mapbox-vector-tile
Requires-Dist: enum34 ; python_version < "3"
Requires-Dist: more-itertools (<6.0.0) ; python_version < "3"
Requires-Dist: typing ; python_version < "3.4"
